requsete/__init__.py
requsete-0.5.dist-info/LICENSE
requsete-0.5.dist-info/METADATA
requsete-0.5.dist-info/WHEEL
requsete-0.5.dist-info/top_level.txt
requsete-0.5.dist-info/RECORD
